checkyoself-0.1.4.dist-info/METADATA
checkyoself-0.1.4.dist-info/WHEEL
checkyoself-0.1.4.dist-info/entry_points.txt
checkyoself-0.1.4.dist-info/licenses/COPYING
checkyoself-0.1.4.dist-info/licenses/LICENSES/AGPL-3.0-or-later.txt
checkyoself-0.1.4.dist-info/licenses/LICENSES/CC-BY-4.0.txt
checkyoself-0.1.4.dist-info/licenses/LICENSES/CC-BY-SA-4.0.txt
checkyoself-0.1.4.dist-info/licenses/LICENSES/CC0-1.0.txt
checkyoself-0.1.4.dist-info/licenses/LICENSES/LicenseRef-DCO-1.1-license.txt
checkyoself/__init__.py
checkyoself/chikkity.py
checkyoself/kb/__init__.py
checkyoself/kb/apt.yml
checkyoself/kb/apt.yml.license
checkyoself/kb/bin.yml
checkyoself/kb/bin.yml.license
checkyoself/kb/path.yml
checkyoself/kb/path.yml.license
checkyoself-0.1.4.dist-info/RECORD
