Metadata-Version: 2.1
Name: checkyoself
Version: 0.1.4
Summary: Which online repositories does my system rely on?
Author-Email: David Seaward <david@librem.one>
License: AGPL-3.0-or-later
Project-URL: Source, https://gitlab.com/lfdo/checkyoself
Project-URL: Project, https://lofidevops.neocities.org
Requires-Python: >=3.10
Requires-Dist: click>=8.1.3
Requires-Dist: parse>=1.19.0
Requires-Dist: ruamel-yaml>=0.17.21
